aiohttp_parameter_parser/__init__.py
aiohttp_parameter_parser/core.py
tests/__init__.py
aiohttp_parameter_parser-0.3.dist-info/LICENSE
aiohttp_parameter_parser-0.3.dist-info/METADATA
aiohttp_parameter_parser-0.3.dist-info/WHEEL
aiohttp_parameter_parser-0.3.dist-info/top_level.txt
aiohttp_parameter_parser-0.3.dist-info/RECORD
