Metadata-Version: 2.1
Name: aiohttp-parameter-parser
Version: 0.3
Summary: Declare and validate HTTP query and path parameters in aiohttp
Home-page: https://github.com/isvinogradov/aiohttp-parameter-parser
Author: Ivan Vinogradov
Author-email: isvinogradov@gmail.com
License: UNKNOWN
Platform: UNKNOWN
Classifier: Programming Language :: Python :: 3
Classifier: License :: OSI Approved :: MIT License
Classifier: Operating System :: OS Independent
Classifier: Intended Audience :: Developers
Classifier: Topic :: Software Development :: Libraries :: Python Modules
Classifier: Topic :: Internet
Requires-Python: >=3.6
